oak/__init__.py
oak/data_engine.py
oak/dataset.py
oak/prompts.py
oak/topic_tree.py
oak/utils.py
oak_data-0.1.0.dist-info/METADATA
oak_data-0.1.0.dist-info/WHEEL
oak_data-0.1.0.dist-info/top_level.txt
oak_data-0.1.0.dist-info/RECORD
